dash_planet/DashPlanet.py
dash_planet/__init__.py
dash_planet/_imports_.py
dash_planet/dash_planet.min.js
dash_planet/dash_planet.min.js.map
dash_planet/metadata.json
dash_planet/package-info.json
dash_planet-0.0.2.dist-info/LICENSE
dash_planet-0.0.2.dist-info/METADATA
dash_planet-0.0.2.dist-info/WHEEL
dash_planet-0.0.2.dist-info/top_level.txt
dash_planet-0.0.2.dist-info/RECORD
