Metadata-Version: 2.1
Name: dash-planet
Version: 0.0.2
Summary: react planet for dash
Author: Pip Install Python <pipinstallpython@gmail.com>
License: MIT
Classifier: Framework :: Dash
License-File: LICENSE
